ophinode/__init__.py
ophinode/__main__.py
ophinode/exceptions/__init__.py
ophinode/exceptions/nodes.py
ophinode/exceptions/rendering.py
ophinode/exceptions/site.py
ophinode/nodes/__init__.py
ophinode/nodes/base.py
ophinode/nodes/html/__init__.py
ophinode/nodes/html/core.py
ophinode/nodes/html/templates.py
ophinode/nodes/html/elements/__init__.py
ophinode/nodes/html/elements/camelcase.py
ophinode/nodes/html/elements/fullname.py
ophinode/nodes/html/elements/lowercase.py
ophinode/rendering/__init__.py
ophinode/rendering/render_node.py
ophinode/site/__init__.py
ophinode/site/build_contexts.py
ophinode/site/core.py
ophinode/site/dependency.py
ophinode/site/page_definition.py
ophinode/site/page_group.py
ophinode-0.0.1a13.dist-info/METADATA
ophinode-0.0.1a13.dist-info/WHEEL
ophinode-0.0.1a13.dist-info/licenses/LICENSE
ophinode-0.0.1a13.dist-info/RECORD
