Metadata-Version: 2.4
Name: ophinode
Version: 0.0.1a13
Summary: A static site generator written in Python
Project-URL: Homepage, https://github.com/deflatedlatte/ophinode
Project-URL: Issues, https://github.com/deflatedlatte/ophinode/issues
Author-email: deflatedlatte <deflatedlatte@gmail.com>
License-File: LICENSE
Classifier: License :: OSI Approved :: MIT License
Classifier: Operating System :: OS Independent
Classifier: Programming Language :: Python :: 3
Requires-Python: >=3.6
